odoo/addons/hr_employee_multi_company/README.rst
odoo/addons/hr_employee_multi_company/__init__.py
odoo/addons/hr_employee_multi_company/__manifest__.py
odoo/addons/hr_employee_multi_company/i18n/hr_employee_multi_company.pot
odoo/addons/hr_employee_multi_company/i18n/it.po
odoo/addons/hr_employee_multi_company/readme/CONTRIBUTORS.md
odoo/addons/hr_employee_multi_company/readme/DESCRIPTION.md
odoo/addons/hr_employee_multi_company/security/hr_employee.xml
odoo/addons/hr_employee_multi_company/static/description/icon.png
odoo/addons/hr_employee_multi_company/static/description/index.html
odoo_addon_hr_employee_multi_company-18.0.1.0.0.3.dist-info/METADATA
odoo_addon_hr_employee_multi_company-18.0.1.0.0.3.dist-info/WHEEL
odoo_addon_hr_employee_multi_company-18.0.1.0.0.3.dist-info/top_level.txt
odoo_addon_hr_employee_multi_company-18.0.1.0.0.3.dist-info/RECORD
